mifaser/__init__.py
mifaser/__main__.py
mifaser/bionode.py
mifaser/caller.py
mifaser/cli.py
mifaser/external.py
mifaser/run.py
mifaser/alignment/__init__.py
mifaser/alignment/parse.py
mifaser/annotation/__init__.py
mifaser/annotation/analysis.py
mifaser/annotation/annotate.py
mifaser/annotation/mapping.py
mifaser/database/GS/database.dmnd
mifaser/database/GS/ec_annotation.tsv
mifaser/database/GS/ec_mapping.tsv
mifaser/database/GS+/database.dmnd
mifaser/database/GS+/ec_annotation.tsv
mifaser/database/GS+/ec_mapping.tsv
mifaser/diamond/linux/diamond
mifaser/diamond/osx/diamond
mifaser/diamond/win/diamond.exe
mifaser/translate/__init__.py
mifaser/translate/gene.py
mifaser/translate/peptideBreak2.py
mifaser/translate/read.py
mifaser-1.60.dist-info/LICENSE.md
mifaser-1.60.dist-info/METADATA
mifaser-1.60.dist-info/WHEEL
mifaser-1.60.dist-info/entry_points.txt
mifaser-1.60.dist-info/top_level.txt
mifaser-1.60.dist-info/RECORD
