Metadata-Version: 2.1
Name: mifaser
Version: 1.60
Summary: a python package for super-fast and accurate annotation of molecular functionality
Home-page: https://bitbucket.org/bromberglab/mifaser
Author: Chengsheng Zhu, Maximilian Miller
Author-email: mmiller@bromberglab.com
License: NPOSL-3.0
Project-URL: Bug Tracker, https://bitbucket.org/bromberglab/mifaser/issues
Project-URL: Documentation, https://bitbucket.org/bromberglab/mifaser/wiki/docs
Project-URL: Source Code, https://bitbucket.org/bromberglab/mifaser
Keywords: microbiome,metagenome,function annotation
Platform: UNKNOWN
Classifier: Development Status :: 5 - Production/Stable
Classifier: Intended Audience :: Science/Research
Classifier: Topic :: Scientific/Engineering :: Bio-Informatics
Classifier: Programming Language :: Python :: 3
Classifier: Programming Language :: Python :: 3.6
Classifier: Programming Language :: Python :: 3.7
Classifier: Programming Language :: Python :: 3.8
Classifier: Natural Language :: English
Classifier: Operating System :: OS Independent
Requires-Python: >=3.6
